vds_api_client/__init__.py
vds_api_client/api_cli.py
vds_api_client/api_v2.py
vds_api_client/requester.py
vds_api_client/types.py
vds_api_client/vds_api_base.py
vds_api_client-2.2.0.dist-info/AUTHORS.rst
vds_api_client-2.2.0.dist-info/LICENSE.txt
vds_api_client-2.2.0.dist-info/METADATA
vds_api_client-2.2.0.dist-info/WHEEL
vds_api_client-2.2.0.dist-info/entry_points.txt
vds_api_client-2.2.0.dist-info/top_level.txt
vds_api_client-2.2.0.dist-info/RECORD
