Metadata-Version: 2.1
Name: vds-api-client
Version: 2.2.0
Summary: VanderSat API client package
Home-page: https://www.planet.com
Author: Teije
Author-email: teije@planet.com
License: mit
Project-URL: Source Code, https://github.com/vandersat/vds-api-client
Project-URL: PyPI, https://pypi.org/project/vds-api-client/
Project-URL: API Documentation, https://docs.vandersat.com/user/api_user_guide.html
Platform: any
Classifier: Development Status :: 4 - Beta
Classifier: Programming Language :: Python
Requires-Python: <4,>=3.6
License-File: LICENSE.txt
License-File: AUTHORS.rst
Requires-Dist: requests
Requires-Dist: click >=7
Requires-Dist: click-datetime
Requires-Dist: pandas
Requires-Dist: retrying
Requires-Dist: joblib
Requires-Dist: future
Provides-Extra: testing
Requires-Dist: pytest ; extra == 'testing'
Requires-Dist: pytest-cov ; extra == 'testing'
